ouroboros_graph/__init__.py
ouroboros_graph/ouroboros_graph.py
ouroboros_graph-0.0.2.dist-info/LICENSE
ouroboros_graph-0.0.2.dist-info/METADATA
ouroboros_graph-0.0.2.dist-info/WHEEL
ouroboros_graph-0.0.2.dist-info/top_level.txt
ouroboros_graph-0.0.2.dist-info/RECORD
