Metadata-Version: 2.1
Name: ouroboros-graph
Version: 0.0.2
Summary: A Graph Abstract Data Type
Home-page: https://github.com/williamvietnguyen/ouroboros-graph
Author: William Nguyen
Author-email: williamvnguyen2@gmail.com
License: UNKNOWN
Keywords: python,graph,data,structure,data-structure
Platform: UNKNOWN
Classifier: Development Status :: 1 - Planning
Classifier: Intended Audience :: Developers
Classifier: Programming Language :: Python :: 3
Classifier: Operating System :: Unix
Classifier: Operating System :: MacOS :: MacOS X
Classifier: Operating System :: Microsoft :: Windows
License-File: LICENSE
